mia/__init__.py
mia/__version__.py
mia/mia_gui.py
mia/startup.py
mia/dl/DeepLearning.py
mia/dl/__init__.py
mia/dl/data/__init__.py
mia/dl/data/imagedata.py
mia/dl/data/labels.py
mia/dl/loss/__init__.py
mia/dl/loss/classification_losses.py
mia/dl/loss/loss_functions.py
mia/dl/loss/losses.py
mia/dl/loss/regression_losses.py
mia/dl/loss/segmentation_losses.py
mia/dl/machine_learning/__init__.py
mia/dl/machine_learning/deploy.prototxt
mia/dl/machine_learning/grabcut_segmentation.py
mia/dl/machine_learning/hed.py
mia/dl/machine_learning/dextr/__init__.py
mia/dl/machine_learning/dextr/classifiers.py
mia/dl/machine_learning/dextr/dextr.py
mia/dl/machine_learning/dextr/dextr_segmentation.py
mia/dl/machine_learning/dextr/helpers.py
mia/dl/machine_learning/dextr/resnet.py
mia/dl/machine_learning/segment_anything/__init__.py
mia/dl/machine_learning/segment_anything/automatic_mask_generator.py
mia/dl/machine_learning/segment_anything/build_sam.py
mia/dl/machine_learning/segment_anything/predictor.py
mia/dl/machine_learning/segment_anything/sam.py
mia/dl/machine_learning/segment_anything/modeling/__init__.py
mia/dl/machine_learning/segment_anything/modeling/common.py
mia/dl/machine_learning/segment_anything/modeling/image_encoder.py
mia/dl/machine_learning/segment_anything/modeling/mask_decoder.py
mia/dl/machine_learning/segment_anything/modeling/prompt_encoder.py
mia/dl/machine_learning/segment_anything/modeling/sam.py
mia/dl/machine_learning/segment_anything/modeling/transformer.py
mia/dl/machine_learning/segment_anything/utils/__init__.py
mia/dl/machine_learning/segment_anything/utils/amg.py
mia/dl/machine_learning/segment_anything/utils/onnx.py
mia/dl/machine_learning/segment_anything/utils/transforms.py
mia/dl/method/__init__.py
mia/dl/method/classification.py
mia/dl/method/mode.py
mia/dl/method/objectcounting.py
mia/dl/method/pixelbasedprediction.py
mia/dl/method/segmentation.py
mia/dl/method/undefinedmode.py
mia/dl/metric/__init__.py
mianalyzer-0.3.1.dist-info/LICENSE
mianalyzer-0.3.1.dist-info/METADATA
mianalyzer-0.3.1.dist-info/WHEEL
mianalyzer-0.3.1.dist-info/entry_points.txt
mianalyzer-0.3.1.dist-info/top_level.txt
mianalyzer-0.3.1.dist-info/RECORD
