Metadata-Version: 2.1
Name: mianalyzer
Version: 0.3.1
Summary: MIA, deep learning based Microscopic Image Analyzer
Home-page: https://github.com/MIAnalyzer/MIA/
Author: Nils Koerber
Project-URL: Homepage, https://github.com/MIAnalyzer/MIA/
Project-URL: Bug Tracker, https://github.com/MIAnalyzer/MIA/issues
Classifier: Programming Language :: Python :: 3
Classifier: License :: OSI Approved :: GNU General Public License v3 (GPLv3)
Classifier: Operating System :: OS Independent
Requires-Python: >=3.6
License-File: LICENSE
